dlinfer/__init__.py
dlinfer/framework/__init__.py
dlinfer/framework/lmdeploy_ext/__init__.py
dlinfer/framework/lmdeploy_ext/cudagraph/__init__.py
dlinfer/framework/lmdeploy_ext/cudagraph/ascend_cudagraph.py
dlinfer/framework/lmdeploy_ext/cudagraph/camb_cudagraph.py
dlinfer/framework/lmdeploy_ext/cudagraph/maca_cudagraph.py
dlinfer/framework/lmdeploy_ext/cudagraph/ppu_cudagraph.py
dlinfer/framework/lmdeploy_ext/device/__init__.py
dlinfer/framework/lmdeploy_ext/device/ascend.py
dlinfer/framework/lmdeploy_ext/device/camb.py
dlinfer/framework/lmdeploy_ext/quants/__init__.py
dlinfer/framework/lmdeploy_ext/quants/ascend_awq.py
dlinfer/framework/torch_npu_ext/__init__.py
dlinfer/framework/torch_npu_ext/aclgraph.py
dlinfer/framework/transformers_ext/__init__.py
dlinfer/framework/transformers_ext/cogvlm.py
dlinfer/framework/transformers_ext/internlm2.py
dlinfer/framework/transformers_ext/internvl.py
dlinfer/framework/transformers_ext/patch.py
dlinfer/graph/__init__.py
dlinfer/graph/custom_op.py
dlinfer/graph/dicp/__init__.py
dlinfer/graph/dicp/dynamo_bridge/__init__.py
dlinfer/graph/dicp/dynamo_bridge/compile.py
dlinfer/graph/dicp/dynamo_bridge/compile_fx.py
dlinfer/graph/dicp/dynamo_bridge/conversion.py
dlinfer/graph/dicp/dynamo_bridge/decompositions.py
dlinfer/graph/dicp/dynamo_bridge/graph.py
dlinfer/graph/dicp/dynamo_bridge/op_transformer.py
dlinfer/graph/dicp/dynamo_bridge/operator.py
dlinfer/graph/dicp/dynamo_bridge/pt_patch.py
dlinfer/graph/dicp/dynamo_bridge/torch_version.py
dlinfer/graph/dicp/dynamo_bridge/utils.py
dlinfer/graph/dicp/vendor/__init__.py
dlinfer/graph/dicp/vendor/AtbGraph/__init__.py
dlinfer/graph/dicp/vendor/AtbGraph/atb_op.py
dlinfer/graph/dicp/vendor/AtbGraph/compile_job.py
dlinfer/graph/dicp/vendor/AtbGraph/config.py
dlinfer/graph/dicp/vendor/AtbGraph/conversion.py
dlinfer/graph/dicp/vendor/AtbGraph/ext_ops.py
dlinfer/graph/dicp/vendor/AtbGraph/infer_res_utils.py
dlinfer/graph/dicp/vendor/AtbGraph/opset_convert.py
dlinfer_ascend-0.2.5.dist-info/licenses/LICENSE
dlinfer_ascend-0.2.5.dist-info/METADATA
dlinfer_ascend-0.2.5.dist-info/WHEEL
dlinfer_ascend-0.2.5.dist-info/entry_points.txt
dlinfer_ascend-0.2.5.dist-info/top_level.txt
dlinfer_ascend-0.2.5.dist-info/RECORD
