Metadata-Version: 2.4
Name: dlinfer-ascend
Version: 0.2.5
Summary: DeepLink Inference Extension
Home-page: https://github.com/DeepLink-org/dlinfer
Classifier: Programming Language :: Python :: 3.10
Classifier: Programming Language :: Python :: 3.11
Classifier: Intended Audience :: Developers
Classifier: Operating System :: POSIX :: Linux
Requires-Python: >=3.10, <3.12
License-File: LICENSE
Requires-Dist: transformers
Requires-Dist: torch<2.9.0,>=2.3.1
Requires-Dist: torch-npu<2.9.0,>=2.3.1
Requires-Dist: torchvision<0.24.0,>=0.18.1
Requires-Dist: importlib-metadata
Requires-Dist: pyyaml
Requires-Dist: decorator
Requires-Dist: attrs
Requires-Dist: psutil
Requires-Dist: absl-py
Requires-Dist: cloudpickle
Requires-Dist: ml-dtypes
Requires-Dist: scipy
Requires-Dist: tornado
Dynamic: classifier
Dynamic: description
Dynamic: description-content-type
Dynamic: home-page
Dynamic: license-file
Dynamic: requires-dist
Dynamic: requires-python
Dynamic: summary
